aiodecorator/__init__.py
aiodecorator/common.py
aiodecorator/py.typed
aiodecorator/repeat.py
aiodecorator/schedule.py
aiodecorator/throttle.py
aiodecorator-3.0.4.dist-info/licenses/LICENSE
aiodecorator-3.0.4.dist-info/METADATA
aiodecorator-3.0.4.dist-info/WHEEL
aiodecorator-3.0.4.dist-info/top_level.txt
aiodecorator-3.0.4.dist-info/RECORD
