Metadata-Version: 2.4
Name: aiodecorator
Version: 3.0.4
Summary: Binance Python SDK
Author-email: kaelzhang <i+github@kael.me>
Project-URL: Homepage, https://github.com/kaelzhang/python-aiodecorator
Classifier: Programming Language :: Python
Classifier: Programming Language :: Python :: 3.6
Classifier: Programming Language :: Python :: 3.7
Classifier: Programming Language :: Python :: 3.8
Classifier: Programming Language :: Python :: 3.9
Classifier: Programming Language :: Python :: 3.10
Classifier: Programming Language :: Python :: 3.11
Classifier: Programming Language :: Python :: 3.12
Classifier: Natural Language :: English
Classifier: Intended Audience :: Developers
Classifier: Operating System :: OS Independent
Classifier: Development Status :: 4 - Beta
Classifier: Topic :: Utilities
Requires-Python: >=3.6
License-File: LICENSE
Provides-Extra: dev
Requires-Dist: codecov; extra == "dev"
Requires-Dist: coverage; extra == "dev"
Requires-Dist: ruff; extra == "dev"
Requires-Dist: pytest; extra == "dev"
Requires-Dist: pytest-asyncio; extra == "dev"
Requires-Dist: pytest-cov; extra == "dev"
Requires-Dist: twine; extra == "dev"
Requires-Dist: setuptools; extra == "dev"
Requires-Dist: mypy; extra == "dev"
Requires-Dist: build; extra == "dev"
Dynamic: license-file
